indicador_iqt/__init__.py
indicador_iqt/data_analysis/__init__.py
indicador_iqt/data_analysis/analisar_dataframe.py
indicador_iqt/data_analysis/calcular_indicadores.py
indicador_iqt/data_analysis/carregadar_dados.py
indicador_iqt/data_analysis/classificar_indicadores.py
indicador_iqt/data_analysis/visualizar_graficos.py
indicador_iqt/map_tools/__init__.py
indicador_iqt/map_tools/camadas.py
indicador_iqt/map_tools/carregar_camadas.py
indicador_iqt/map_tools/cricao_mapa.py
indicador_iqt/map_tools/estilos.py
indicador_iqt/utils/__init__.py
indicador_iqt/utils/associador.py
indicador_iqt/utils/cores.py
indicador_iqt/utils/execptions.py
indicador_iqt/utils/modelos.py
indicador_iqt/utils/utils.py
indicador_iqt-0.1.8.dist-info/LICENSE
indicador_iqt-0.1.8.dist-info/METADATA
indicador_iqt-0.1.8.dist-info/WHEEL
indicador_iqt-0.1.8.dist-info/RECORD
