Metadata-Version: 2.3
Name: indicador_iqt
Version: 0.1.8
Summary: Automatizar o cálculo do Índice de Qualidade do Transporte (IQT). O IQT é uma métrica essencial para a análise e otimização do transporte público, considerando fatores como pontualidade, frequência de atendimento, cumprimento de itinerários e infraestrutura.
License: Apache-2.0
Keywords: transporte,IQT,GIS,análise espacial,transporte público
Author: Yago Maia
Author-email: yagohenriquev123@gmail.com
Requires-Python: >=3.7
Classifier: License :: OSI Approved :: Apache Software License
Classifier: Programming Language :: Python :: 3
Classifier: Programming Language :: Python :: 3.7
Classifier: Programming Language :: Python :: 3.8
Classifier: Programming Language :: Python :: 3.9
Classifier: Programming Language :: Python :: 3.10
Classifier: Programming Language :: Python :: 3.11
Classifier: Programming Language :: Python :: 3.12
Classifier: Programming Language :: Python :: 3.13
Requires-Dist: fiona
Requires-Dist: folium
Requires-Dist: geopandas
Requires-Dist: matplotlib
Requires-Dist: numpy
Requires-Dist: pandas
Requires-Dist: seaborn
Requires-Dist: shapely
Project-URL: Homepage, https://github.com/YagoMaia/indicador_iqt
Project-URL: Repository, https://github.com/YagoMaia/indicador_iqt
